<?xml version="1.0" encoding="utf-8" ?><dwsync><file name="404.php" server="projet.vetementsurmesure.eu//httpdocs/" local="3392022264" remote="12009173132" /><file name="archive.php" server="projet.vetementsurmesure.eu//httpdocs/" local="3403766240" remote="12009173132" /><file name="author.php" server="projet.vetementsurmesure.eu//httpdocs/" local="3390716584" remote="12009173132" /><file name="category.php" server="projet.vetementsurmesure.eu//httpdocs/" local="3390716584" remote="12009173132" /><file name="comments.php" server="projet.vetementsurmesure.eu//httpdocs/" local="3390623046" remote="12009173192" /><file name="content-aside.php" server="projet.vetementsurmesure.eu//httpdocs/" local="3393223124" remote="12009173192" /><file name="content-featured.php" server="projet.vetementsurmesure.eu//httpdocs/" local="3391686226" remote="12009173192" /><file name="content-gallery.php" server="projet.vetementsurmesure.eu//httpdocs/" local="3404706014" remote="12009173192" /><file name="content-image.php" server="projet.vetementsurmesure.eu//httpdocs/" local="3406360732" remote="12009173192" /><file name="content-intro.php" server="projet.vetementsurmesure.eu//httpdocs/" local="3391686226" remote="12009173192" /><file name="content-link.php" server="projet.vetementsurmesure.eu//httpdocs/" local="3393223124" remote="12009173192" /><file name="content-page.php" server="projet.vetementsurmesure.eu//httpdocs/" local="3392287070" remote="12009173192" /><file name="content-quote.php" server="projet.vetementsurmesure.eu//httpdocs/" local="3393223124" remote="12009173192" /><file name="content-single.php" server="projet.vetementsurmesure.eu//httpdocs/" local="3406362230" remote="12009173192" /><file name="content-status.php" server="projet.vetementsurmesure.eu//httpdocs/" local="3393223124" remote="12009173192" /><file name="content.php" server="projet.vetementsurmesure.eu//httpdocs/" local="3393223124" remote="12009173192" /><file name="editor-style-rtl.css" server="projet.vetementsurmesure.eu//httpdocs/" local="3402663458" remote="12009173192" /><file name="editor-style.css" server="projet.vetementsurmesure.eu//httpdocs/" local="3393232344" remote="12009173192" /><file name="footer.php" server="projet.vetementsurmesure.eu//httpdocs/" local="3404492200" remote="12009173192" /><file name="functions.php" server="projet.vetementsurmesure.eu//httpdocs/" local="3406360732" remote="12009173252" /><file name="header.php" server="projet.vetementsurmesure.eu//httpdocs/" local="3391686226" remote="12009173252" /><file name="image.php" server="projet.vetementsurmesure.eu//httpdocs/" local="3406360732" remote="12009173252" /><file name="index.php" server="projet.vetementsurmesure.eu//httpdocs/" local="3390716584" remote="12009173432" /><file name="license.txt" server="projet.vetementsurmesure.eu//httpdocs/" local="3386185716" remote="12009173492" /><file name="page.php" server="projet.vetementsurmesure.eu//httpdocs/" local="3404708450" remote="12009173492" /><file name="readme.txt" server="projet.vetementsurmesure.eu//httpdocs/" local="3386185716" remote="12009173492" /><file name="rtl.css" server="projet.vetementsurmesure.eu//httpdocs/" local="3404706468" remote="12009173492" /><file name="screenshot.png" server="projet.vetementsurmesure.eu//httpdocs/" local="3393178880" remote="12009173552" /><file name="search.php" server="projet.vetementsurmesure.eu//httpdocs/" local="3388561570" remote="12009173552" /><file name="searchform.php" server="projet.vetementsurmesure.eu//httpdocs/" local="3390623046" remote="12009173552" /><file name="showcase.php" server="projet.vetementsurmesure.eu//httpdocs/" local="3404708450" remote="12009173552" /><file name="sidebar-footer.php" server="projet.vetementsurmesure.eu//httpdocs/" local="3388265672" remote="12009173552" /><file name="sidebar-page.php" server="projet.vetementsurmesure.eu//httpdocs/" local="3404708450" remote="12009173552" /><file name="sidebar.php" server="projet.vetementsurmesure.eu//httpdocs/" local="3391686226" remote="12009173552" /><file name="single.php" server="projet.vetementsurmesure.eu//httpdocs/" local="3392028150" remote="12009173552" /><file name="style.css" server="projet.vetementsurmesure.eu//httpdocs/" local="3406360732" remote="12009173552" /><file name="tag.php" server="projet.vetementsurmesure.eu//httpdocs/" local="3390716584" remote="12009173552" /></dwsync>